scad_format/__init__.py
scad_format/__main__.py
scad_format/cli.py
scad_format/config.py
scad_format/formatter.py
scad_format/tokenizer.py
scad_format-1.0.0.dist-info/licenses/LICENSE
scad_format-1.0.0.dist-info/METADATA
scad_format-1.0.0.dist-info/WHEEL
scad_format-1.0.0.dist-info/entry_points.txt
scad_format-1.0.0.dist-info/top_level.txt
scad_format-1.0.0.dist-info/RECORD
