Metadata-Version: 2.4
Name: scad-format
Version: 1.0.0
Summary: A code formatter for OpenSCAD files, similar to clang-format
License: MIT
Project-URL: Homepage, https://github.com/ashleyharris-maptek-com-au/scad-format
Project-URL: Repository, https://github.com/ashleyharris-maptek-com-au/scad-format
Keywords: openscad,formatter,code-formatting,scad
Classifier: Development Status :: 3 - Alpha
Classifier: Intended Audience :: Developers
Classifier: License :: OSI Approved :: MIT License
Classifier: Programming Language :: Python :: 3
Classifier: Programming Language :: Python :: 3.8
Classifier: Programming Language :: Python :: 3.9
Classifier: Programming Language :: Python :: 3.10
Classifier: Programming Language :: Python :: 3.11
Classifier: Programming Language :: Python :: 3.12
Classifier: Programming Language :: Python :: 3.13
Classifier: Programming Language :: Python :: 3.14
Classifier: Topic :: Software Development :: Quality Assurance
Requires-Python: >=3.8
License-File: LICENSE
Provides-Extra: dev
Requires-Dist: pytest>=7.0.0; extra == "dev"
Requires-Dist: pytest-cov>=4.0.0; extra == "dev"
Provides-Extra: build
Requires-Dist: pyinstaller>=6.0.0; extra == "build"
Dynamic: license-file
